ctrf/BaseMetadataReport.py
ctrf/CommonTestReportPlugin.py
ctrf/Report.py
ctrf/TestObject.py
ctrf/__init__.py
ctrf/main.py
pytest_json_ctrf-0.3.6.dist-info/METADATA
pytest_json_ctrf-0.3.6.dist-info/WHEEL
pytest_json_ctrf-0.3.6.dist-info/entry_points.txt
pytest_json_ctrf-0.3.6.dist-info/top_level.txt
pytest_json_ctrf-0.3.6.dist-info/RECORD
