Metadata-Version: 2.4
Name: pytest-json-ctrf
Version: 0.3.6
Summary: Pytest plugin to generate json report in CTRF (Common Test Report Format)
Author: Oleksii Ostapov
Project-URL: Infopulse, https://infopulse.com/
Project-URL: Homepage, https://github.com/infopulse/pytest-common-test-report-json
Classifier: Framework :: Pytest
Classifier: Programming Language :: Python :: 3
Classifier: License :: OSI Approved :: MIT License
Classifier: Operating System :: OS Independent
Requires-Python: >=3.9
Requires-Dist: pytest>6.0.0
